{
  "fail_reason": [
    "aw1_latest:not_pass",
    "aw1_queue:queue_item_count_not_zero",
    "aw1_queue:model_improvement_candidate_count_not_zero"
  ],
  "fetched_at": "2026-06-28T00:07:44Z",
  "generated_at": "2026-06-28T00:07:44Z",
  "github_actions": true,
  "network": "GitHub Actions hosted runner",
  "no_fake_pass": true,
  "pass": false,
  "repository": "muahosting/aw1-public-truth-watchdog",
  "results": [
    {
      "body_hash": "ac18224593f3109c7ac2e98b09633a6f1c86a797c52992bcb5847ffb49a85d5b",
      "cache_control": "no-store, no-cache, must-revalidate, proxy-revalidate, max-age=0",
      "contains_PASS_WITH_NEWER_RUNTIME_LOG": false,
      "contains_stale_latest_true": false,
      "effective_verdict": "BLOCKED",
      "elapsed_ms": 1569,
      "etag": "\"251ea-655451ca368d6\"",
      "generated_at": "2026-06-28T00:06:01Z",
      "last_modified": "Sun, 28 Jun 2026 00:06:21 GMT",
      "latest_effective_verdict": "BLOCKED",
      "latest_verdict": "BLOCKED",
      "model_improvement_candidate_count": 2,
      "name": "aw1_latest",
      "newest_receipt_name": "aw1_offline_fix_5pct_public_selector_latest_canary_history_after_runtime_pass_20260627T105801Z.json",
      "queue_item_count": 2,
      "stale_latest": false,
      "status_code": 200,
      "url": "https://aw1.awai.vn/log/latest.json",
      "verdict": "BLOCKED"
    },
    {
      "body_hash": "c947748293b0747296b40b6762cc2989c6e25254ced9480980b3de5d924e2a70",
      "cache_control": "no-store, no-cache, must-revalidate, proxy-revalidate, max-age=0",
      "contains_PASS_WITH_NEWER_RUNTIME_LOG": false,
      "contains_stale_latest_true": false,
      "elapsed_ms": 670,
      "etag": "\"2591-655451ca370a6\"",
      "generated_at": "2026-06-28T00:06:01Z",
      "last_modified": "Sun, 28 Jun 2026 00:06:21 GMT",
      "name": "aw1_index",
      "status_code": 200,
      "url": "https://aw1.awai.vn/log/"
    },
    {
      "body_hash": "709d1e5db0dd5289ea9c623f927452fbe23e951ac4c56506eb829e641e5977d1",
      "cache_control": "no-store, no-cache, must-revalidate, proxy-revalidate, max-age=0",
      "contains_PASS_WITH_NEWER_RUNTIME_LOG": false,
      "contains_stale_latest_true": false,
      "elapsed_ms": 636,
      "etag": "\"1287-655451ca368d6\"",
      "generated_at": "2026-06-28T00:06:21Z",
      "last_modified": "Sun, 28 Jun 2026 00:06:21 GMT",
      "model_improvement_candidate_count": 2,
      "name": "aw1_queue",
      "queue_item_count": 2,
      "status_code": 200,
      "url": "https://aw1.awai.vn/log/model_improvement_queue_public.json"
    },
    {
      "body_hash": "1c1d9e085e63cd4fcdf128413a0fe77581f63440f9acbae32ec20bd13478b44c",
      "cache_control": "no-store, no-cache, must-revalidate, proxy-revalidate, max-age=0",
      "contains_PASS_WITH_NEWER_RUNTIME_LOG": false,
      "contains_stale_latest_true": false,
      "elapsed_ms": 1108,
      "etag": "\"39e0-655450e972210\"",
      "generated_at": "2026-06-28T00:02:26Z",
      "last_modified": "Sun, 28 Jun 2026 00:02:26 GMT",
      "name": "chat_latest",
      "render_result": "PASS",
      "status_code": 200,
      "url": "https://chat.awai.vn/log/latest.json",
      "verdict": "PASS"
    }
  ],
  "run_attempt": "1",
  "run_id": "28305927172",
  "runner_os": "Linux",
  "vantage_id": "external_github_actions",
  "verdict": "FAIL"
}
