{
  "fail_reason": [
    "chat_latest:render_result_not_pass"
  ],
  "fetched_at": "2026-06-26T18:11:12Z",
  "generated_at": "2026-06-26T18:11:12Z",
  "github_actions": true,
  "network": "GitHub Actions hosted runner",
  "no_fake_pass": true,
  "pass": false,
  "repository": "muahosting/aw1-public-truth-watchdog",
  "results": [
    {
      "body_hash": "e2256dc385e0b08d4d25690f9258a40b48bb7b63738a92f645785f105a6ac8b1",
      "cache_control": "no-store, no-cache, must-revalidate, proxy-revalidate, max-age=0",
      "contains_PASS_WITH_NEWER_RUNTIME_LOG": false,
      "contains_stale_latest_true": false,
      "effective_verdict": "PASS",
      "elapsed_ms": 2360,
      "etag": "\"23ec0-6552c0555f1d3\"",
      "generated_at": "2026-06-26T18:10:01Z",
      "last_modified": "Fri, 26 Jun 2026 18:10:16 GMT",
      "latest_effective_verdict": "PASS",
      "latest_verdict": "PASS",
      "model_improvement_candidate_count": 0,
      "name": "aw1_latest",
      "newest_receipt_name": "aw1_post_full_replace_route_invariants_20260625T132944Z.json",
      "queue_item_count": 0,
      "stale_latest": false,
      "status_code": 200,
      "url": "https://aw1.awai.vn/log/latest.json",
      "verdict": "PASS"
    },
    {
      "body_hash": "85f8167c07b54dfb2ccada00e0f48bc772b1b3453c91c954f020f6388d805200",
      "cache_control": "no-store, no-cache, must-revalidate, proxy-revalidate, max-age=0",
      "contains_PASS_WITH_NEWER_RUNTIME_LOG": false,
      "contains_stale_latest_true": false,
      "elapsed_ms": 1699,
      "etag": "\"2073-6552c0555f5bb\"",
      "generated_at": "2026-06-26T18:10:01Z",
      "last_modified": "Fri, 26 Jun 2026 18:10:16 GMT",
      "name": "aw1_index",
      "status_code": 200,
      "url": "https://aw1.awai.vn/log/"
    },
    {
      "body_hash": "8723cb6548ddcd5029c0c3e6b721b2b3d55912097b17c1499f9ed60ed5b8cab2",
      "cache_control": "no-store, no-cache, must-revalidate, proxy-revalidate, max-age=0",
      "contains_PASS_WITH_NEWER_RUNTIME_LOG": false,
      "contains_stale_latest_true": false,
      "elapsed_ms": 627,
      "etag": "\"1d3a-6552c0555edeb\"",
      "generated_at": "2026-06-26T18:10:16Z",
      "last_modified": "Fri, 26 Jun 2026 18:10:16 GMT",
      "model_improvement_candidate_count": 0,
      "name": "aw1_queue",
      "queue_item_count": 0,
      "status_code": 200,
      "url": "https://aw1.awai.vn/log/model_improvement_queue_public.json"
    },
    {
      "body_hash": "ae797ee8a915aef36f1d0c36962660228375fc38a0f5efadffbed42fb67b2993",
      "cache_control": "no-store, no-cache, must-revalidate, proxy-revalidate, max-age=0",
      "contains_PASS_WITH_NEWER_RUNTIME_LOG": false,
      "contains_stale_latest_true": false,
      "elapsed_ms": 976,
      "etag": "\"3a2e-65528a1e78f40\"",
      "generated_at": "2026-06-26T14:07:43Z",
      "last_modified": "Fri, 26 Jun 2026 14:07:43 GMT",
      "name": "chat_latest",
      "render_result": "DEGRADED",
      "status_code": 200,
      "url": "https://chat.awai.vn/log/latest.json",
      "verdict": "PASS"
    }
  ],
  "run_attempt": "1",
  "run_id": "28256620851",
  "runner_os": "Linux",
  "vantage_id": "external_github_actions",
  "verdict": "FAIL"
}
