{
  "fail_reason": [],
  "fetched_at": "2026-07-06T09:03:32Z",
  "generated_at": "2026-07-06T09:03:32Z",
  "github_actions": true,
  "network": "GitHub Actions hosted runner",
  "no_fake_pass": true,
  "pass": true,
  "repository": "muahosting/aw1-public-truth-watchdog",
  "results": [
    {
      "body_hash": "e0139fe79a9a7a07da2af20407cc002235e61bfe7bd4f9a39d52205ff28cc973",
      "cache_control": "no-cache",
      "contains_PASS_WITH_NEWER_RUNTIME_LOG": false,
      "contains_stale_latest_true": false,
      "effective_verdict": "PASS",
      "elapsed_ms": 2253,
      "etag": "\"96249-655ed8c1b66a2\"",
      "generated_at": "2026-07-06T09:02:13Z",
      "last_modified": "Mon, 06 Jul 2026 09:03:26 GMT",
      "latest_effective_verdict": "PASS",
      "latest_verdict": "PASS",
      "model_improvement_candidate_count": 0,
      "name": "aw1_latest",
      "newest_receipt_name": "aw1_model_factory_expanded_baseline_runtime_scoring_latest.txt",
      "queue_item_count": 0,
      "stale_latest": false,
      "status_code": 200,
      "url": "https://aw1.awai.vn/log/latest.json",
      "verdict": "PASS"
    },
    {
      "body_hash": "7f63a1407ca473d54da55a23b5c77fb505c315c69f751eb46f16c2bc7f43eb5b",
      "cache_control": "no-cache",
      "contains_PASS_WITH_NEWER_RUNTIME_LOG": false,
      "contains_stale_latest_true": false,
      "elapsed_ms": 688,
      "etag": "\"2b8f-655ed8c1b7e12\"",
      "generated_at": "2026-07-06T09:02:13Z",
      "last_modified": "Mon, 06 Jul 2026 09:03:26 GMT",
      "name": "aw1_index",
      "status_code": 200,
      "url": "https://aw1.awai.vn/log/"
    },
    {
      "body_hash": "c460dc86b84a6f20429d75ace8f525831731d836fbd7f201aef33bd78af81946",
      "cache_control": "no-cache",
      "contains_PASS_WITH_NEWER_RUNTIME_LOG": false,
      "contains_stale_latest_true": false,
      "elapsed_ms": 664,
      "etag": "\"1dd3-655ed8c1b66a2\"",
      "generated_at": "2026-07-06T09:03:26Z",
      "last_modified": "Mon, 06 Jul 2026 09:03:26 GMT",
      "model_improvement_candidate_count": 0,
      "name": "aw1_queue",
      "queue_item_count": 0,
      "status_code": 200,
      "url": "https://aw1.awai.vn/log/model_improvement_queue_public.json"
    },
    {
      "body_hash": "87019669d8782778c496af69b929e7d6e4f9fb595ccbc04ccf4c8b22c676bb68",
      "cache_control": "no-store, no-cache, must-revalidate, proxy-revalidate, max-age=0",
      "contains_PASS_WITH_NEWER_RUNTIME_LOG": false,
      "contains_stale_latest_true": false,
      "elapsed_ms": 1134,
      "etag": "\"2fe2-655ed78587c78\"",
      "generated_at": "2026-07-03T12:05:25Z",
      "last_modified": "Mon, 06 Jul 2026 08:57:54 GMT",
      "name": "chat_latest",
      "render_result": "PASS",
      "status_code": 200,
      "url": "https://chat.awai.vn/log/latest.json",
      "verdict": "PASS"
    }
  ],
  "run_attempt": "1",
  "run_id": "28780181281",
  "runner_os": "Linux",
  "vantage_id": "external_github_actions",
  "verdict": "PASS"
}
