{
  "fail_reason": [],
  "fetched_at": "2026-06-30T22:51:40Z",
  "generated_at": "2026-06-30T22:51:40Z",
  "github_actions": true,
  "network": "GitHub Actions hosted runner",
  "no_fake_pass": true,
  "pass": true,
  "repository": "muahosting/aw1-public-truth-watchdog",
  "results": [
    {
      "body_hash": "7ebc7e35b8110d9d0f7cdb0ed835fbdcf609e3a7904a898e537880d305ac0fdc",
      "cache_control": "no-store, no-cache, must-revalidate, proxy-revalidate, max-age=0",
      "contains_PASS_WITH_NEWER_RUNTIME_LOG": false,
      "contains_stale_latest_true": false,
      "effective_verdict": "PASS",
      "elapsed_ms": 1897,
      "etag": "\"219d5-65580667d4923\"",
      "generated_at": "2026-06-30T22:50:01Z",
      "last_modified": "Tue, 30 Jun 2026 22:50:23 GMT",
      "latest_effective_verdict": "PASS",
      "latest_verdict": "PASS",
      "model_improvement_candidate_count": 0,
      "name": "aw1_latest",
      "newest_receipt_name": "aw1_autopilot_v4_16_guarded_1pct_rollback_sentry_20260630T135257Z.json",
      "queue_item_count": 0,
      "stale_latest": false,
      "status_code": 200,
      "url": "https://aw1.awai.vn/log/latest.json",
      "verdict": "PASS"
    },
    {
      "body_hash": "34fc360b9aab3b5ab3dec67856b1fc7819f9ab1506c4202d95229c2aaf439540",
      "cache_control": "no-store, no-cache, must-revalidate, proxy-revalidate, max-age=0",
      "contains_PASS_WITH_NEWER_RUNTIME_LOG": false,
      "contains_stale_latest_true": false,
      "elapsed_ms": 898,
      "etag": "\"20b1-65580667d50f3\"",
      "generated_at": "2026-06-30T22:50:01Z",
      "last_modified": "Tue, 30 Jun 2026 22:50:23 GMT",
      "name": "aw1_index",
      "status_code": 200,
      "url": "https://aw1.awai.vn/log/"
    },
    {
      "body_hash": "28d4cb41112a0e270caab804b771b401d3823d388087806b1fe933abb4e5c81b",
      "cache_control": "no-store, no-cache, must-revalidate, proxy-revalidate, max-age=0",
      "contains_PASS_WITH_NEWER_RUNTIME_LOG": false,
      "contains_stale_latest_true": false,
      "elapsed_ms": 896,
      "etag": "\"1db5-65580667d4923\"",
      "generated_at": "2026-06-30T22:50:23Z",
      "last_modified": "Tue, 30 Jun 2026 22:50:23 GMT",
      "model_improvement_candidate_count": 0,
      "name": "aw1_queue",
      "queue_item_count": 0,
      "status_code": 200,
      "url": "https://aw1.awai.vn/log/model_improvement_queue_public.json"
    },
    {
      "body_hash": "743480de3f86a72f08bf447cfb49cabe17403dc2ec703c1669c15b3b1ac94212",
      "cache_control": "no-store, no-cache, must-revalidate, proxy-revalidate, max-age=0",
      "contains_PASS_WITH_NEWER_RUNTIME_LOG": false,
      "contains_stale_latest_true": false,
      "elapsed_ms": 1220,
      "etag": "\"2f95-6557844c34bb0\"",
      "generated_at": "2026-06-26T13:02:48Z",
      "last_modified": "Tue, 30 Jun 2026 13:08:18 GMT",
      "name": "chat_latest",
      "render_result": "PASS",
      "status_code": 200,
      "url": "https://chat.awai.vn/log/latest.json",
      "verdict": "PASS"
    }
  ],
  "run_attempt": "1",
  "run_id": "28480993192",
  "runner_os": "Linux",
  "vantage_id": "external_github_actions",
  "verdict": "PASS"
}
