{
  "fail_reason": [],
  "fetched_at": "2026-07-03T04:26:50Z",
  "generated_at": "2026-07-03T04:26:50Z",
  "github_actions": true,
  "network": "GitHub Actions hosted runner",
  "no_fake_pass": true,
  "pass": true,
  "repository": "muahosting/aw1-public-truth-watchdog",
  "results": [
    {
      "body_hash": "31e31549421e0417b81bfb6225a0fde9eaa39fe53f330cf4bf06a6f16e207be3",
      "cache_control": "no-cache",
      "contains_PASS_WITH_NEWER_RUNTIME_LOG": false,
      "contains_stale_latest_true": false,
      "effective_verdict": "PASS",
      "elapsed_ms": 9234,
      "etag": "\"213ec-655ad5437e8b0\"",
      "generated_at": "2026-07-03T04:26:01Z",
      "last_modified": "Fri, 03 Jul 2026 04:26:30 GMT",
      "latest_effective_verdict": "PASS",
      "latest_verdict": "PASS",
      "model_improvement_candidate_count": 0,
      "name": "aw1_latest",
      "newest_receipt_name": "aw1_model_progress_report_20260703T042401Z.json",
      "queue_item_count": 0,
      "stale_latest": false,
      "status_code": 200,
      "url": "https://aw1.awai.vn/log/latest.json",
      "verdict": "PASS"
    },
    {
      "body_hash": "0778dad8eacc93dac74177fa403f89cbe4eebb9c24e6bb418d9246e777e62cb2",
      "cache_control": "no-cache",
      "contains_PASS_WITH_NEWER_RUNTIME_LOG": false,
      "contains_stale_latest_true": false,
      "elapsed_ms": 644,
      "etag": "\"2958-655ad5437f080\"",
      "generated_at": "2026-07-03T04:26:01Z",
      "last_modified": "Fri, 03 Jul 2026 04:26:30 GMT",
      "name": "aw1_index",
      "status_code": 200,
      "url": "https://aw1.awai.vn/log/"
    },
    {
      "body_hash": "b731deb22b0c28805531d464016099e495a16dca1761d447248227f932261c98",
      "cache_control": "no-cache",
      "contains_PASS_WITH_NEWER_RUNTIME_LOG": false,
      "contains_stale_latest_true": false,
      "elapsed_ms": 6547,
      "etag": "\"1d9e-655ad5437e4c8\"",
      "generated_at": "2026-07-03T04:26:30Z",
      "last_modified": "Fri, 03 Jul 2026 04:26:30 GMT",
      "model_improvement_candidate_count": 0,
      "name": "aw1_queue",
      "queue_item_count": 0,
      "status_code": 200,
      "url": "https://aw1.awai.vn/log/model_improvement_queue_public.json"
    },
    {
      "body_hash": "743480de3f86a72f08bf447cfb49cabe17403dc2ec703c1669c15b3b1ac94212",
      "cache_control": "no-store, no-cache, must-revalidate, proxy-revalidate, max-age=0",
      "contains_PASS_WITH_NEWER_RUNTIME_LOG": false,
      "contains_stale_latest_true": false,
      "elapsed_ms": 827,
      "etag": "\"2f95-655aa65166a28\"",
      "generated_at": "2026-06-26T13:02:48Z",
      "last_modified": "Fri, 03 Jul 2026 00:56:29 GMT",
      "name": "chat_latest",
      "render_result": "PASS",
      "status_code": 200,
      "url": "https://chat.awai.vn/log/latest.json",
      "verdict": "PASS"
    }
  ],
  "run_attempt": "1",
  "run_id": "28638380327",
  "runner_os": "Linux",
  "vantage_id": "external_github_actions",
  "verdict": "PASS"
}
