{
  "fail_reason": [
    "chat_latest:render_result_not_pass"
  ],
  "fetched_at": "2026-06-28T22:35:47Z",
  "generated_at": "2026-06-28T22:35:47Z",
  "github_actions": true,
  "network": "GitHub Actions hosted runner",
  "no_fake_pass": true,
  "pass": false,
  "repository": "muahosting/aw1-public-truth-watchdog",
  "results": [
    {
      "body_hash": "ad531f6b8a4505b1a80a8307322711c540a78094fd1722c5693e09b23940ba67",
      "cache_control": "no-store, no-cache, must-revalidate, proxy-revalidate, max-age=0",
      "contains_PASS_WITH_NEWER_RUNTIME_LOG": false,
      "contains_stale_latest_true": false,
      "effective_verdict": "PASS",
      "elapsed_ms": 1543,
      "etag": "\"2247d-65557f1709367\"",
      "generated_at": "2026-06-28T22:34:01Z",
      "last_modified": "Sun, 28 Jun 2026 22:34:21 GMT",
      "latest_effective_verdict": "PASS",
      "latest_verdict": "PASS",
      "model_improvement_candidate_count": 0,
      "name": "aw1_latest",
      "newest_receipt_name": "aw1_autopilot_v3_rollback_lease_20260628T115248Z.json",
      "queue_item_count": 0,
      "stale_latest": false,
      "status_code": 200,
      "url": "https://aw1.awai.vn/log/latest.json",
      "verdict": "PASS"
    },
    {
      "body_hash": "9480b213617a93ddffb7ed1b280a5d9b446d8bad8d09dee88008e3f9e68c07be",
      "cache_control": "no-store, no-cache, must-revalidate, proxy-revalidate, max-age=0",
      "contains_PASS_WITH_NEWER_RUNTIME_LOG": false,
      "contains_stale_latest_true": false,
      "elapsed_ms": 1306,
      "etag": "\"2093-65557f1709b37\"",
      "generated_at": "2026-06-28T22:34:01Z",
      "last_modified": "Sun, 28 Jun 2026 22:34:21 GMT",
      "name": "aw1_index",
      "status_code": 200,
      "url": "https://aw1.awai.vn/log/"
    },
    {
      "body_hash": "79f1b3da48ece05cdf686206763ee7668eeef80d8d0b4ad940ec61ca329c3ed1",
      "cache_control": "no-store, no-cache, must-revalidate, proxy-revalidate, max-age=0",
      "contains_PASS_WITH_NEWER_RUNTIME_LOG": false,
      "contains_stale_latest_true": false,
      "elapsed_ms": 553,
      "etag": "\"1de8-65557f1709367\"",
      "generated_at": "2026-06-28T22:34:21Z",
      "last_modified": "Sun, 28 Jun 2026 22:34:21 GMT",
      "model_improvement_candidate_count": 0,
      "name": "aw1_queue",
      "queue_item_count": 0,
      "status_code": 200,
      "url": "https://aw1.awai.vn/log/model_improvement_queue_public.json"
    },
    {
      "body_hash": "ec08a036e381616d4a979cc0d3fa7fe23bca69e787d6a321236ac178fed7524f",
      "cache_control": "no-store, no-cache, must-revalidate, proxy-revalidate, max-age=0",
      "contains_PASS_WITH_NEWER_RUNTIME_LOG": false,
      "contains_stale_latest_true": false,
      "elapsed_ms": 811,
      "etag": "\"39e1-65550be66c230\"",
      "generated_at": "2026-06-28T13:59:00Z",
      "last_modified": "Sun, 28 Jun 2026 13:59:00 GMT",
      "name": "chat_latest",
      "render_result": "DEGRADED",
      "status_code": 200,
      "url": "https://chat.awai.vn/log/latest.json",
      "verdict": "PASS"
    }
  ],
  "run_attempt": "1",
  "run_id": "28338317027",
  "runner_os": "Linux",
  "vantage_id": "external_github_actions",
  "verdict": "FAIL"
}
